[
 {"kategory": "schlafErholung", "key": "schlafstunden1", "name": "Schlafstunden", "type": "number", "userKathegory": ["Casual", "Produktivität", "Workaholic", "Sportler", "Gesundheit", "Lifestyle", "Kreativ"]},
 {"kategory": "schlafErholung", "key": "schlafqualitat2", "name": "Schlafqualität", "options": ["Sehr schlecht", "Schlecht", "Okay", "Gut", "Sehr gut"], "type": "enum", "userKathegory": ["Casual", "Produktivität", "Workaholic", "Sportler", "Gesundheit", "Lifestyle", "Kreativ"]},
 {"kategory": "schlafErholung", "key": "einschlafzeit3", "name": "Einschlafzeit", "type": "number", "userKathegory": ["Sportler"]},
 {"kategory": "schlafErholung", "key": "aufwachzeit4", "name": "Aufwachzeit", "type": "number", "userKathegory": ["Produktivität", "Workaholic", "Sportler", "Gesundheit"]},
 {"kategory": "schlafErholung", "key": "einschlafdauer5", "name": "Einschlafdauer", "type": "number", "userKathegory": []},
 {"kategory": "schlafErholung", "key": "nachtlichesaufwachen6", "name": "Nächtliches Aufwachen", "type": "number", "userKathegory": ["Sportler"]},
 {"kategory": "schlafErholung", "key": "mittagsschlaf7", "name": "Mittagsschlaf", "type": "bool", "userKathegory": ["Workaholic", "Sportler"]},
 {"kategory": "schlafErholung", "key": "albtraumegehabt8", "name": "Albträume gehabt", "type": "bool", "userKathegory": []},
 {"kategory": "schlafErholung", "key": "schlafumgebung9", "name": "Schlafumgebung", "options": ["Sehr schlecht", "Schlecht", "Okay", "Gut", "Sehr gut"], "type": "enum", "userKathegory": ["Workaholic", "Sportler"]},
 {"kategory": "schlafErholung", "key": "schlafunterstuzung10", "name": "Schlafunterstüzung", "options": ["Keine", "Medikamente", "Schlafmaske", "Ohrstöpsel", "Andere"], "type": "bool", "userKathegory": ["Sportler"]},
 {"kategory": "schlafErholung", "key": "entspannungvordemschlafen11", "name": "Entspannung vor dem Schlafen", "type": "bool", "userKathegory": []},
 {"kategory": "schlafErholung", "key": "bildschirmzeitvordemschlafen12", "name": "Bildschirmzeit vor dem Schlafen", "type": "number", "userKathegory": ["Produktivität", "Workaholic"]},
 {"kategory": "schlafErholung", "key": "koffeinvordemschlafen13", "name": "Koffein vor dem Schlafen", "type": "bool", "userKathegory": []},
 {"kategory": "schlafErholung", "key": "alkoholvordemschlafen14", "name": "Alkohol vor dem Schlafen", "type": "bool", "userKathegory": []},
 {"kategory": "schlafErholung", "key": "schlafenmitohneunterbrechung15", "name": "Schlafen mit/ohne Unterbrechung", "type": "bool", "userKathegory": []},
 {"kategory": "ernarungKonsum", "key": "mahlzeitenanzahl16", "name": "Mahlzeitenanzahl", "type": "number", "userKathegory": ["Sportler", "Gesundheit"]},
 {"kategory": "ernarungKonsum", "key": "fruhstuckgegessen17", "name": "Frühstück gegessen", "type": "bool", "userKathegory": []},
 {"kategory": "ernarungKonsum", "key": "mittagessengesund18", "name": "Mittagessen gesund", "type": "bool", "userKathegory": []},
 {"kategory": "ernarungKonsum", "key": "kaloriengeschatzt19", "name": "Kalorien geschätzt", "type": "number", "userKathegory": ["Casual", "Produktivität", "Workaholic", "Sportler", "Gesundheit"]},
 {"kategory": "ernarungKonsum", "key": "wasserzufuhrgeschatzt20", "name": "Wasserzufuhr geschätzt", "type": "number", "userKathegory": ["Produktivität", "Workaholic", "Sportler", "Gesundheit"]},
 {"kategory": "ernarungKonsum", "key": "koffeinkonsumiert21", "name": "Koffein konsumiert", "type": "bool", "userKathegory": ["Produktivität", "Workaholic", "Sportler"]},
 {"kategory": "ernarungKonsum", "key": "koffeinmenge22", "name": "Koffeinmenge", "type": "number", "userKathegory": []},
 {"kategory": "ernarungKonsum", "key": "rauchen23", "name": "Rauchen", "type": "bool", "userKathegory": []},
 {"kategory": "ernarungKonsum", "key": "zigarettenanzahl24", "name": "Zigarettenanzahl", "type": "number", "userKathegory": []},
 {"kategory": "ernarungKonsum", "key": "alkoholkonsumiert25", "name": "Alkohol konsumiert", "type": "bool", "userKathegory": ["Workaholic"]},
 {"kategory": "ernarungKonsum", "key": "alkoholmenge26", "name": "Alkoholmenge", "type": "number", "userKathegory": []},
 {"kategory": "ernarungKonsum", "key": "fastfoodgegessen27", "name": "Fast Food gegessen", "type": "bool", "userKathegory": []},
 {"kategory": "ernarungKonsum", "key": "snacksgegessen28", "name": "Snacks gegessen", "type": "bool", "userKathegory": []},
 {"kategory": "ernarungKonsum", "key": "obstgegessen29", "name": "Obst gegessen", "type": "bool", "userKathegory": []},
 {"kategory": "ernarungKonsum", "key": "gemusegegessen30", "name": "Gemüse gegessen", "type": "bool", "userKathegory": []},
 {"kategory": "ernarungKonsum", "key": "obstgemusegegessen31", "name": "Obst/Gemüse gegessen", "type": "bool", "userKathegory": []},
 {"kategory": "ernarungKonsum", "key": "zuckerkonsumiert32", "name": "Zucker konsumiert", "type": "bool", "userKathegory": []},
 {"kategory": "ernarungKonsum", "key": "zuckermenge33", "name": "Zuckermenge", "type": "number", "userKathegory": ["Workaholic", "Sportler"]},
 {"kategory": "ernarungKonsum", "key": "essensort34", "name": "Essensort", "options": ["Daheim", "Office", "Draußen", "Unterwegs", "Andere"], "type": "enum", "userKathegory": []},
 {"kategory": "ernarungKonsum", "key": "essenszeitpunkt35", "name": "Essenszeitpunkt", "options": ["Morgens", "Mittags", "Abends", "Nachts", "Andere"], "type": "enum", "userKathegory": []},
 {"kategory": "ernarungKonsum", "key": "artderernahrung36", "name": "Art der Ernährung", "options": ["Omnivor", "Vegetarisch", "Vegan", "Pescetarisch", "Andere"], "type": "enum", "userKathegory": []},
 {"kategory": "bewegungGesundheit", "key": "sportgemacht37", "name": "Sport gemacht", "type": "bool", "userKathegory": ["Casual", "Produktivität", "Workaholic", "Sportler", "Gesundheit"]},
 {"kategory": "bewegungGesundheit", "key": "sportdauer38", "name": "Sportdauer", "type": "number", "userKathegory": ["Casual", "Workaholic", "Sportler", "Gesundheit"]},
 {"kategory": "bewegungGesundheit", "key": "sportintensitat39", "name": "Sportintensität", "options": ["Kaum Bewegung", "Leicht", "Normal", "Anstrengend", "Maximal"], "type": "enum", "userKathegory": ["Casual", "Produktivität", "Workaholic", "Sportler", "Gesundheit"]},
 {"kategory": "bewegungGesundheit", "key": "schritte40", "name": "Schritte", "type": "number", "userKathegory": ["Casual", "Workaholic", "Gesundheit"]},
 {"kategory": "bewegungGesundheit", "key": "gedehnt41", "name": "Gedehnt", "type": "bool", "userKathegory": ["Sportler", "Gesundheit"]},
 {"kategory": "bewegungGesundheit", "key": "yoga42", "name": "Yoga", "type": "bool", "userKathegory": []},
 {"kategory": "bewegungGesundheit", "key": "spaziergang43", "name": "Spaziergang", "type": "bool", "userKathegory": []},
 {"kategory": "bewegungGesundheit", "key": "fahrradfahren44", "name": "Fahrradfahren", "type": "bool", "userKathegory": []},
 {"kategory": "bewegungGesundheit", "key": "schwimmen45", "name": "Schwimmen", "type": "bool", "userKathegory": []},
 {"kategory": "bewegungGesundheit", "key": "trainingstyp46", "name": "Trainingstyp", "options": ["Strength", "Ausdauer", "Intervall", "Stretch", "Andere"], "type": "enum", "userKathegory": ["Sportler"]},
 {"kategory": "bewegungGesundheit", "key": "trainingsort47", "name": "Trainingsort", "options": ["Fitnessstudio", "Zuhause", "Draußen", "Schwimmbad", "Andere"], "type": "enum", "userKathegory": ["Sportler"]},
 {"kategory": "bewegungGesundheit", "key": "trainingszeitpunkt48", "name": "Trainingszeitpunkt", "options": ["Morgens", "Mittags", "Abends", "Nachts", "Andere"], "type": "enum", "userKathegory": ["Produktivität", "Workaholic", "Sportler", "Gesundheit"]},
 {"kategory": "bewegungGesundheit", "key": "teamsport49", "name": "Teamsport", "type": "bool", "userKathegory": []},
 {"kategory": "bewegungGesundheit", "key": "herzfrequenzdurchschnitt50", "name": "Herzfrequenz (Durchschnitt)", "type": "number", "userKathegory": ["Sportler"]},
 {"kategory": "bewegungGesundheit", "key": "herzfrequenzmaximum51", "name": "Herzfrequenz (Maximum)", "type": "number", "userKathegory": ["Sportler"]},
 {"kategory": "bewegungGesundheit", "key": "gewicht52", "name": "Gewicht", "type": "number", "userKathegory": ["Sportler"]},
 {"kategory": "stimmungEmotionen", "key": "stimmung53", "name": "Stimmung", "options": ["Am Boden", "Niedrig", "Geht so", "Gut drauf", "Top Laune"], "type": "enum", "userKathegory": ["Casual", "Produktivität", "Workaholic", "Sportler", "Gesundheit", "Achtsamkeit", "Lifestyle", "Kreativ"]},
 {"kategory": "stimmungEmotionen", "key": "stresslevel54", "name": "Stresslevel", "options": ["Kaum Stress", "Etwas Stress", "Normal", "Hoch", "Maximal"], "type": "enum", "userKathegory": ["Casual", "Produktivität", "Workaholic", "Sportler", "Gesundheit", "Achtsamkeit"]},
 {"kategory": "stimmungEmotionen", "key": "energielevel55", "name": "Energielevel", "options": ["Tot", "Müde", "Geht", "Fit", "Übervoll"], "type": "enum", "userKathegory": ["Casual", "Produktivität", "Workaholic", "Sportler", "Gesundheit", "Achtsamkeit"]},
 {"kategory": "stimmungEmotionen", "key": "motivationslevel56", "name": "Motivationslevel", "options": ["Leer", "Kaum", "Okay", "Motiviert", "Supermotiviert"], "type": "enum", "userKathegory": ["Produktivität", "Workaholic", "Sportler", "Lifestyle", "Kreativ"]},
 {"kategory": "stimmungEmotionen", "key": "kreativitatslevel57", "name": "Kreativitätslevel", "options": ["Leer", "Angekratzt", "Okay", "Kreativ", "Inspiration pur"], "type": "enum", "userKathegory": ["Kreativ"]},
 {"kategory": "stimmungEmotionen", "key": "angstlevel58", "name": "Angstlevel", "options": ["Keine Sorge", "Leichte Sorge", "Unruhe", "Angst", "Panik"], "type": "enum", "userKathegory": ["Workaholic"]},
 {"kategory": "stimmungEmotionen", "key": "traurigkeitlevel59", "name": "Traurigkeitlevel", "options": ["Keine", "Leicht", "Spürbar", "Stark", "Tieftraurig"], "type": "enum", "userKathegory": ["Workaholic"]},
 {"kategory": "stimmungEmotionen", "key": "freudelevel60", "name": "Freudelevel", "options": ["Trüb", "Leicht hell", "Hell", "Sehr hell", "Strahlend"], "type": "enum", "userKathegory": ["Lifestyle", "Kreativ"]},
 {"kategory": "stimmungEmotionen", "key": "argerwutlevel61", "name": "Ärger/Wut Level", "options": ["Kein Ärger", "Unruhig", "Verärgert", "Wütend", "Außer Kontrolle"], "type": "enum", "userKathegory": []},
 {"kategory": "stimmungEmotionen", "key": "dankbarkeitslevel62", "name": "Dankbarkeitslevel", "options": ["Undankbar", "Wenig", "Okay", "Dankbar", "Sehr dankbar"], "type": "enum", "userKathegory": []},
 {"kategory": "stimmungEmotionen", "key": "gelassenheitslevel63", "name": "Gelassenheitslevel", "options": ["Keine", "Etwas", "Mittel", "Viel", "Vollkommene Ruhe"], "type": "enum", "userKathegory": []},
 {"kategory": "stimmungEmotionen", "key": "emotionaleausgeglichenheit64", "name": "Emotionale Ausgeglichenheit", "options": ["Keine Balance", "Wenig", "Halb", "Viel", "Perfekt"], "type": "enum", "userKathegory": ["Achtsamkeit"]},
 {"kategory": "arbeitProduktivität", "key": "arbeitsstunden65", "name": "Arbeitsstunden", "type": "number", "userKathegory": ["Casual", "Produktivität", "Workaholic"]},
 {"kategory": "arbeitProduktivität", "key": "fokuskonzentrationsphasen66", "name": "Fokus/Konzentrations Phasen", "type": "number", "userKathegory": ["Workaholic"]},
 {"kategory": "arbeitProduktivität", "key": "pausenanzahl67", "name": "Pausenanzahl", "type": "number", "userKathegory": ["Workaholic"]},
 {"kategory": "arbeitProduktivität", "key": "prokrastinationerlebt68", "name": "Prokrastination erlebt", "type": "bool", "userKathegory": ["Produktivität"]},
 {"kategory": "arbeitProduktivität", "key": "wichtigeaufgabeabgeschlossen69", "name": "Wichtige Aufgabe abgeschlossen", "type": "bool", "userKathegory": ["Produktivität", "Workaholic"]},
 {"kategory": "arbeitProduktivität", "key": "meetingscalls70", "name": "Meetings/Calls", "type": "number", "userKathegory": ["Workaholic"]},
 {"kategory": "arbeitProduktivität", "key": "kreativitat71", "name": "Kreativität", "options": ["Keine Ideen", "Wenig", "Mittel", "Viel", "Inspiration pur"], "type": "enum", "userKathegory": []},
 {"kategory": "arbeitProduktivität", "key": "arbeitszufriedenheit72", "name": "Arbeitszufriedenheit", "options": ["Katastrophe", "Schwach", "Geht so", "Gut", "Top"], "type": "enum", "userKathegory": []},
 {"kategory": "arbeitProduktivität", "key": "produktivitat73", "name": "Produktivität", "options": ["Stillstand", "Langsam", "Normal", "Produktiv", "Superproduktiv"], "type": "enum", "userKathegory": ["Casual", "Produktivität", "Workaholic"]},
 {"kategory": "arbeitProduktivität", "key": "arbeitsumgebungangenehm74", "name": "Arbeitsumgebung angenehm", "type": "bool", "userKathegory": ["Produktivität", "Workaholic"]},
 {"kategory": "arbeitProduktivität", "key": "arbeitsstresslevel75", "name": "Arbeitsstresslevel", "options": ["Entspannt", "Gering", "Mittel", "Stark", "Kollapsnah"], "type": "enum", "userKathegory": []},
 {"kategory": "arbeitProduktivität", "key": "todolisteerledigt76", "name": "To-Do Liste erledigt (%)", "type": "number", "userKathegory": []},
 {"kategory": "arbeitProduktivität", "key": "zufriedenheitmitarbeit77", "name": "Zufriedenheit mit Arbeit", "options": ["Katastrophe", "Unzufrieden", "Neutral", "Zufrieden", "Sehr zufrieden"], "type": "enum", "userKathegory": ["Casual"]},
 {"kategory": "sozialesBeziehungen", "key": "zeitmitfreunden78", "name": "Zeit mit Freunden", "type": "number", "userKathegory": ["Produktivität", "Sozial", "Lifestyle"]},
 {"kategory": "sozialesBeziehungen", "key": "zeitmirfreundenverbracht79", "name": "Zeit mir Freunden verbracht", "type": "bool", "userKathegory": []},
 {"kategory": "sozialesBeziehungen", "key": "zeitmitkollegen80", "name": "Zeit mit Kollegen", "type": "number", "userKathegory": ["Workaholic", "Sportler", "Sozial"]},
 {"kategory": "sozialesBeziehungen", "key": "zeitmitfamilie81", "name": "Zeit mit Familie", "type": "number", "userKathegory": ["Produktivität", "Workaholic", "Sozial", "Lifestyle"]},
 {"kategory": "sozialesBeziehungen", "key": "zeitmitfamilieverbracht82", "name": "Zeit mit Familie verbracht", "type": "bool", "userKathegory": []},
 {"kategory": "sozialesBeziehungen", "key": "konflikteerlebt83", "name": "Konflikte erlebt", "type": "bool", "userKathegory": ["Sozial"]},
 {"kategory": "sozialesBeziehungen", "key": "sozialeinteraktionen84", "name": "Soziale Interaktionen", "type": "number", "userKathegory": ["Casual", "Sozial"]},
 {"kategory": "sozialesBeziehungen", "key": "positivesozialeinteraktionen85", "name": "Positive soziale Interaktionen", "type": "number", "userKathegory": ["Casual", "Sozial"]},
 {"kategory": "sozialesBeziehungen", "key": "negativesozialeinteraktionen86", "name": "Negative soziale Interaktionen", "type": "number", "userKathegory": ["Casual", "Sozial"]},
 {"kategory": "sozialesBeziehungen", "key": "einsamkeitempfunden87", "name": "Einsamkeit empfunden", "options": ["Verbunden", "Leicht allein", "Einsamer", "Sehr einsam", "Abgeschottet"], "type": "enum", "userKathegory": []},
 {"kategory": "sozialesBeziehungen", "key": "anderengeholfen88", "name": "Anderen geholfen", "type": "bool", "userKathegory": ["Sozial"]},
 {"kategory": "sozialesBeziehungen", "key": "partnerzeit89", "name": "Partner-Zeit", "type": "number", "userKathegory": ["Sozial"]},
 {"kategory": "sozialesBeziehungen", "key": "intimitatgehabt90", "name": "Intimität gehabt", "type": "bool", "userKathegory": ["Sozial"]},
 {"kategory": "sozialesBeziehungen", "key": "neueleutegetroffen91", "name": "Neue Leute getroffen", "type": "bool", "userKathegory": ["Sozial"]},
 {"kategory": "sozialesBeziehungen", "key": "kommunikation92", "name": "Kommunikation", "options": ["Giftig", "Anstrengend", "Neutral", "Angenehm", "Super angenehm"], "type": "enum", "userKathegory": ["Sozial"]},
 {"kategory": "mentalesWohlbefinden", "key": "meditation93", "name": "Meditation", "type": "bool", "userKathegory": ["Workaholic", "Sportler", "Gesundheit", "Achtsamkeit"]},
 {"kategory": "mentalesWohlbefinden", "key": "meditationdauer94", "name": "Meditationdauer", "type": "number", "userKathegory": ["Achtsamkeit"]},
 {"kategory": "mentalesWohlbefinden", "key": "meditationsintensitat95", "name": "Meditations Intensität", "options": ["Null", "Leicht", "Spürbar", "Intensiv", "Tiefenmeditation"], "type": "enum", "userKathegory": ["Achtsamkeit"]},
 {"kategory": "mentalesWohlbefinden", "key": "atemubungengemacht96", "name": "Atemübungen gemacht", "type": "bool", "userKathegory": ["Achtsamkeit"]},
 {"kategory": "mentalesWohlbefinden", "key": "achtsamkeitsubungen97", "name": "Achtsamkeitsübungen", "type": "bool", "userKathegory": ["Achtsamkeit"]},
 {"kategory": "mentalesWohlbefinden", "key": "journalinggemacht98", "name": "Journaling gemacht", "type": "bool", "userKathegory": ["Achtsamkeit", "Kreativ"]},
 {"kategory": "mentalesWohlbefinden", "key": "bildschirmfreiezeit99", "name": "Bildschirmfreie Zeit", "type": "number", "userKathegory": ["Gesundheit", "Achtsamkeit"]},
 {"kategory": "mentalesWohlbefinden", "key": "sozialemediennutzung100", "name": "Soziale Medien Nutzung", "type": "number", "userKathegory": ["Casual", "Produktivität", "Workaholic", "Achtsamkeit", "Lifestyle", "Kreativ"]},
 {"kategory": "mentalesWohlbefinden", "key": "fernsehnstreamingzeit101", "name": "Fernsehn/Streaming Zeit", "type": "number", "userKathegory": []},
 {"kategory": "mentalesWohlbefinden", "key": "lesen102", "name": "Lesen", "type": "number", "userKathegory": []},
 {"kategory": "mentalesWohlbefinden", "key": "entspannungstechniken103", "name": "Entspannungstechniken", "type": "bool", "userKathegory": []},
 {"kategory": "mentalesWohlbefinden", "key": "dankbarkeitsubung104", "name": "Dankbarkeitsübung", "type": "bool", "userKathegory": ["Achtsamkeit"]},
 {"kategory": "mentalesWohlbefinden", "key": "positiveaffirmationen105", "name": "Positive Affirmationen", "type": "bool", "userKathegory": ["Achtsamkeit", "Kreativ"]},
 {"kategory": "mentalesWohlbefinden", "key": "mentalegesundheit106", "name": "Mentale Gesundheit", "options": ["Am Boden", "Schwach", "Neutral", "Stabil", "Sehr stabil"], "type": "enum", "userKathegory": []},
 {"kategory": "mentalesWohlbefinden", "key": "stressbewaltigung107", "name": "Stressbewältigung", "options": ["Versagt", "Schwach", "Geht so", "Gut", "Top"], "type": "enum", "userKathegory": []},
 {"kategory": "mentalesWohlbefinden", "key": "uberforderung108", "name": "Überforderung", "type": "number", "userKathegory": ["Workaholic"]},
 {"kategory": "freizeitHobbys", "key": "hobbyausgeubt109", "name": "Hobbyausgeübt", "type": "bool", "userKathegory": ["Casual", "Produktivität", "Workaholic", "Sozial", "Lifestyle", "Kreativ"]},
 {"kategory": "freizeitHobbys", "key": "musikgehort110", "name": "Musik gehört", "type": "bool", "userKathegory": ["Kreativ"]},
 {"kategory": "freizeitHobbys", "key": "musiziert111", "name": "Musiziert", "type": "bool", "userKathegory": ["Kreativ"]},
 {"kategory": "freizeitHobbys", "key": "instrumentgespielt112", "name": "Instrument gespielt", "type": "bool", "userKathegory": ["Kreativ"]},
 {"kategory": "freizeitHobbys", "key": "kunsthandwerkgemacht113", "name": "Kunsthandwerk gemacht", "type": "bool", "userKathegory": ["Kreativ"]},
 {"kategory": "freizeitHobbys", "key": "malenzeichnen114", "name": "Malen/Zeichnen", "type": "bool", "userKathegory": ["Kreativ"]},
 {"kategory": "freizeitHobbys", "key": "fotografieren115", "name": "Fotografieren", "type": "bool", "userKathegory": ["Kreativ"]},
 {"kategory": "freizeitHobbys", "key": "tanzen116", "name": "Tanzen", "type": "bool", "userKathegory": ["Kreativ"]},
 {"kategory": "freizeitHobbys", "key": "buchergelesen117", "name": "Bücher gelesen", "type": "number", "userKathegory": ["Kreativ"]},
 {"kategory": "freizeitHobbys", "key": "gaming118", "name": "Gaming", "type": "number", "userKathegory": []},
 {"kategory": "freizeitHobbys", "key": "serienfilmegeschaut119", "name": "Serien/Filme geschaut", "type": "number", "userKathegory": ["Kreativ"]},
 {"kategory": "freizeitHobbys", "key": "kreativtatig120", "name": "Kreativ tätig", "type": "bool", "userKathegory": []},
 {"kategory": "freizeitHobbys", "key": "kochenbacken121", "name": "Kochen/Backen", "type": "bool", "userKathegory": []},
 {"kategory": "freizeitHobbys", "key": "neueaktivitatausprobiert122", "name": "Neue Aktivität ausprobiert", "type": "bool", "userKathegory": []},
 {"kategory": "freizeitHobbys", "key": "naturzeit123", "name": "Naturzeit", "type": "number", "userKathegory": []},
 {"kategory": "freizeitHobbys", "key": "reisenausfluggemacht124", "name": "Reisen/Ausflug gemacht", "type": "bool", "userKathegory": ["Lifestyle"]},
 {"kategory": "gesundheitKorper", "key": "arztbesuch125", "name": "Arztbesuch", "type": "bool", "userKathegory": []},
 {"kategory": "gesundheitKorper", "key": "schmerzengehabt126", "name": "Schmerzen gehabt", "type": "bool", "userKathegory": ["Sportler", "Gesundheit"]},
 {"kategory": "gesundheitKorper", "key": "schmerzintensitat127", "name": "Schmerzintensität", "options": ["Kein Schmerz", "Leicht", "Spürbar", "Stark", "Sehr stark"], "type": "enum", "userKathegory": ["Sportler", "Gesundheit"]},
 {"kategory": "gesundheitKorper", "key": "schmerzort128", "name": "Schmerzort", "options": ["Kopf", "Rücken", "Gelenke", "Muskeln", "Andere"], "type": "enum", "userKathegory": ["Sportler"]},
 {"kategory": "gesundheitKorper", "key": "migranegehabt129", "name": "Migräne gehabt", "type": "bool", "userKathegory": []},
 {"kategory": "gesundheitKorper", "key": "kopfschmerzen130", "name": "Kopfschmerzen", "type": "bool", "userKathegory": []},
 {"kategory": "gesundheitKorper", "key": "menstruation131", "name": "Menstruation", "type": "bool", "userKathegory": []},
 {"kategory": "gesundheitKorper", "key": "allergiesymptome132", "name": "Allergiesymptome", "type": "bool", "userKathegory": []},
 {"kategory": "gesundheitKorper", "key": "medikamentegenommen133", "name": "Medikamente genommen", "type": "bool", "userKathegory": []},
 {"kategory": "gesundheitKorper", "key": "blutdruck134", "name": "Blutdruck", "type": "number", "userKathegory": []},
 {"kategory": "gesundheitKorper", "key": "korpertemperatur135", "name": "Körpertemperatur", "type": "number", "userKathegory": []},
 {"kategory": "umwelLifestyle", "key": "wetter136", "name": "Wetter", "options": ["Sonnig", "Bewölkt", "Regen", "Schnee", "Windig", "Andere"], "type": "enum", "userKathegory": ["Lifestyle"]},
 {"kategory": "umwelLifestyle", "key": "luftqualitat137", "name": "Luftqualität", "options": ["Smog", "Dunst", "Okay", "Frisch", "Klar"], "type": "enum", "userKathegory": ["Lifestyle"]},
 {"kategory": "umwelLifestyle", "key": "auentemperatur138", "name": "Außentemperatur", "type": "number", "userKathegory": ["Lifestyle"]},
 {"kategory": "umwelLifestyle", "key": "larmpegel139", "name": "Lärmpegel", "options": ["Ruhe", "Gering", "Normal", "Laut", "Sehr laut"], "type": "enum", "userKathegory": ["Lifestyle"]},
 {"kategory": "umwelLifestyle", "key": "lichtverhaltnisse140", "name": "Lichtverhältnisse", "options": ["Dunkel", "Halbdunkel", "Normal", "Hell", "Grell"], "type": "enum", "userKathegory": ["Lifestyle"]},
 {"kategory": "umwelLifestyle", "key": "wohnumgebungangenehm141", "name": "Wohnumgebung angenehm", "type": "bool", "userKathegory": []},
 {"kategory": "umwelLifestyle", "key": "arbeitsumgebungangenehm142", "name": "Arbeitsumgebung angenehm", "type": "bool", "userKathegory": []},
 {"kategory": "umwelLifestyle", "key": "zeitdrauen143", "name": "Zeit draußen", "type": "number", "userKathegory": ["Sozial"]},
 {"kategory": "umwelLifestyle", "key": "reizuberflutungerlebt144", "name": "Reizüberflutung erlebt", "type": "bool", "userKathegory": []},
 {"kategory": "umwelLifestyle", "key": "ordnungzuhauseaufgeraumt145", "name": "Ordnung/Zuhause aufgeräumt", "type": "bool", "userKathegory": []},
 {"kategory": "umwelLifestyle", "key": "ordnungamarbeitsplatz146", "name": "Ordnung am Arbeitsplatz", "options": ["Katastrophe", "Schlecht", "Okay", "Gut", "Top"], "type": "enum", "userKathegory": ["Lifestyle"]},
 {"kategory": "umwelLifestyle", "key": "ordnungzuhause147", "name": "Ordnung Zuhause", "options": ["Durcheinander", "Unordentlich", "Neutral", "Ordentlich", "Perfekt"], "type": "enum", "userKathegory": ["Lifestyle"]},
 {"kategory": "umwelLifestyle", "key": "umweltbewusstgehandelt148", "name": "Umweltbewusst gehandelt", "type": "bool", "userKathegory": []},
 {"kategory": "umwelLifestyle", "key": "naturerlebt149", "name": "Natur erlebt", "type": "bool", "userKathegory": ["Lifestyle", "Kreativ"]},
 {"kategory": "umwelLifestyle", "key": "digitaldetoxgemacht150", "name": "Digital Detox gemacht", "type": "bool", "userKathegory": ["Lifestyle", "Kreativ"]},
 {"kategory": "umwelLifestyle", "key": "nachrichtenmedienkonsum151", "name": "Nachrichten/Medienkonsum", "type": "number", "userKathegory": []}
]